ipaPy2/MS2compare.py
ipaPy2/PeakMLIO.py
ipaPy2/__init__.py
ipaPy2/ipa.py
ipaPy2/iterations.py
ipaPy2/util.py
ipaPy2-1.3.0.dist-info/LICENSE
ipaPy2-1.3.0.dist-info/METADATA
ipaPy2-1.3.0.dist-info/WHEEL
ipaPy2-1.3.0.dist-info/top_level.txt
ipaPy2-1.3.0.dist-info/RECORD
