Metadata-Version: 2.1
Name: ipaPy2
Version: 1.3.0
Summary: Integrated Probabilistic Annotation (IPA) 2.0 - Python implementation 
Home-page: https://github.com/francescodc87/ipaPy2
Author: Dr Francesco Del Carratore, Juraj Borka
Author-email: francescodc87@gmail.com
License: MIT
Platform: UNKNOWN
License-File: LICENSE
Requires-Dist: pandas
Requires-Dist: molmass (==2021.6.18)
Requires-Dist: scipy (==1.8.1)
Requires-Dist: tqdm (==4.64.0)
